google_tasks_to_todoist/cli.py
google_tasks_to_todoist/converter.py
google_tasks_to_todoist-0.1.1.dist-info/METADATA
google_tasks_to_todoist-0.1.1.dist-info/WHEEL
google_tasks_to_todoist-0.1.1.dist-info/entry_points.txt
google_tasks_to_todoist-0.1.1.dist-info/licenses/LICENSE
google_tasks_to_todoist-0.1.1.dist-info/RECORD
