Metadata-Version: 2.4
Name: google-tasks-to-todoist
Version: 0.1.1
Summary: A utility to convert Google Tasks JSON exports to Todoist CSV format.
Project-URL: Homepage, https://github.com/exploids/google-tasks-to-todoist
Project-URL: Repository, https://github.com/exploids/google-tasks-to-todoist
License-File: LICENSE
Requires-Python: >=3.13
